{
  "Aries": {
    "Overall": "Aries, today's planetary alignments bring a blend of dynamism and introspection.  Saturn in your sign encourages discipline, while the Sun and Jupiter in Gemini spark your intellect and communication skills.  Harness this energy to achieve your goals, but remember to pace yourself and avoid impulsive decisions.",
    "Auspicious Time": "9:00 AM - 10:30 AM",
    "Inauspicious Time": "4:30 PM - 6:00 PM",
    "Daily Wisdom & Suggestions": "Embrace calculated risks, but always prioritize mindful planning and execution.  Listen to your intuition; it will guide you towards sound decisions.",
    "Detailed Predictions": {
      "Love & Relationships": {
        "Text": "Existing relationships may require more open communication.  Singles, focus on self-improvement before seeking new connections.  Be honest with your feelings, even if it's challenging.",
        "percentage": "70"
      },
      "Career & Money": {
        "Text": "Career opportunities may present themselves unexpectedly.  Be prepared to seize the moment.  However, avoid major financial commitments today.  Focus on careful planning and budgeting.",
        "percentage": "80"
      },
      "Health & Wellness": {
        "Text": "Prioritize self-care through mindful practices like stretching or meditation.  Listen to your body's cues and rest when needed.  Avoid overexertion to prevent burnout.",
        "percentage": "85"
      },
      "Personal Growth": {
        "Text": "Embrace challenges as opportunities for learning and growth.  Reflect on your progress and identify areas where you can further enhance your skills and knowledge.  Step outside your comfort zone strategically.",
        "percentage": "75"
      }
    },
    "lucky_elements": {
      "lucky_numbers": [
        7,
        11,
        22,
        34,
        45
      ],
      "lucky_colors": [
        "red",
        "deep blue",
        "forest green",
        "golden yellow"
      ]
    },
    "daily_timeline": [
      {
        "time": "6:00 - 8:00",
        "favorability": "neutral",
        "activity": "Morning reflection or light stretching"
      },
      {
        "time": "8:00 - 10:00",
        "favorability": "favorable",
        "activity": "Focus on important communications and planning"
      },
      {
        "time": "10:00 - 12:00",
        "favorability": "most-favorable",
        "activity": "Tackle creative projects or challenging tasks"
      },
      {
        "time": "12:00 - 14:00",
        "favorability": "neutral",
        "activity": "Lunch break, mindful eating, recharge"
      },
      {
        "time": "14:00 - 16:00",
        "favorability": "favorable",
        "activity": "Collaborative work or detail-oriented tasks"
      },
      {
        "time": "16:00 - 18:00",
        "favorability": "favorable",
        "activity": "Networking, learning, or wrapping up work"
      },
      {
        "time": "18:00 - 20:00",
        "favorability": "unfavorable",
        "activity": "Avoid Financial Decisions during this period"
      },
      {
        "time": "20:00 - 22:00",
        "favorability": "neutral",
        "activity": "Relaxation, reading, or preparing for tomorrow"
      }
    ],
    "personalized_recommendations": {
      "dos": [
        "Embrace new perspectives with an open heart.",
        "Practice active listening to foster understanding.",
        "Schedule brief moments for mindfulness throughout the day."
      ],
      "donts": [
        "Avoid snap judgments in complex situations.",
        "Don't let minor setbacks derail your overall progress.",
        "Refrain from overcommitting your time and energy."
      ]
    }
  },
  "Taurus": {
    "Overall": "Taurus, today's planetary alignment brings a blend of grounded stability and exciting new opportunities.  Venus in your sign enhances your charm and attractiveness, while Uranus encourages you to embrace unexpected changes.  Maintain a balanced approach, grounding yourself amidst the dynamic energy.",
    "Auspicious Time": "9:00 AM - 10:30 AM",
    "Inauspicious Time": "4:30 PM - 6:00 PM",
    "Daily Wisdom & Suggestions": "Embrace mindful moments to navigate the day's energy effectively, and actively listen to deepen connections and understanding.",
    "Detailed Predictions": {
      "Love & Relationships": {
        "Text": "Your romantic relationships will flourish today.  Venus in Taurus amplifies your sensuality and connection, fostering intimacy and understanding.  Single Taureans may encounter exciting new possibilities.",
        "percentage": "90"
      },
      "Career & Money": {
        "Text": "Focus on meticulous work and collaborative efforts.  Avoid impulsive financial decisions.  Strategic planning and detailed execution will lead to success in your professional endeavors.",
        "percentage": "75"
      },
      "Health & Wellness": {
        "Text": "Prioritize self-care and mindful eating.  Engage in gentle exercise and relaxation techniques to maintain a balanced energy flow.  Listen to your body's needs.",
        "percentage": "85"
      },
      "Personal Growth": {
        "Text": "Embrace new perspectives and learning experiences.  Step outside your comfort zone and explore creative avenues for self-expression. This is a time for growth and expansion.",
        "percentage": "70"
      }
    },
    "lucky_elements": {
      "lucky_numbers": [
        7,
        11,
        22,
        34,
        45
      ],
      "lucky_colors": [
        "red",
        "deep blue",
        "forest green",
        "golden yellow"
      ]
    },
    "daily_timeline": [
      {
        "time": "6:00 - 8:00",
        "favorability": "neutral",
        "activity": "Morning reflection or light stretching"
      },
      {
        "time": "8:00 - 10:00",
        "favorability": "favorable",
        "activity": "Focus on important communications and planning"
      },
      {
        "time": "10:00 - 12:00",
        "favorability": "most-favorable",
        "activity": "Tackle creative projects or challenging tasks"
      },
      {
        "time": "12:00 - 14:00",
        "favorability": "neutral",
        "activity": "Lunch break, mindful eating, recharge"
      },
      {
        "time": "14:00 - 16:00",
        "favorability": "favorable",
        "activity": "Collaborative work or detail-oriented tasks"
      },
      {
        "time": "16:00 - 18:00",
        "favorability": "favorable",
        "activity": "Networking, learning, or wrapping up work"
      },
      {
        "time": "18:00 - 20:00",
        "favorability": "unfavorable",
        "activity": "Avoid Financial Decisions during this period"
      },
      {
        "time": "20:00 - 22:00",
        "favorability": "neutral",
        "activity": "Relaxation, reading, or preparing for tomorrow"
      }
    ],
    "personalized_recommendations": {
      "dos": [
        "Embrace new perspectives with an open heart.",
        "Practice active listening to foster understanding.",
        "Schedule brief moments for mindfulness throughout the day."
      ],
      "donts": [
        "Avoid snap judgments in complex situations.",
        "Don't let minor setbacks derail your overall progress.",
        "Refrain from overcommitting your time and energy."
      ]
    }
  },
  "Gemini": {
    "Overall": "Gemini, today's planetary alignment brings a surge of energy and mental clarity.  With the Sun, Mercury, and Jupiter all in your sign, your communication skills are sharp, and opportunities abound.  However, the Moon in Scorpio urges caution; trust your instincts but avoid impulsive decisions.",
    "Auspicious Time": "9:00 AM - 10:30 AM",
    "Inauspicious Time": "4:30 PM - 6:00 PM",
    "Daily Wisdom & Suggestions": "Embrace the power of mindful communication, expressing your thoughts and ideas clearly and with empathy, while simultaneously cultivating patience and understanding in your interactions with others.",
    "Detailed Predictions": {
      "Love & Relationships": {
        "Text": "Singles might encounter exciting new connections, while committed couples should prioritize open and honest communication to navigate any potential misunderstandings.  Focus on strengthening emotional bonds.",
        "percentage": "85"
      },
      "Career & Money": {
        "Text": "Your sharp intellect and communication skills will be invaluable in professional endeavors.  New opportunities may arise, but thorough planning and careful consideration are key before making significant financial decisions. ",
        "percentage": "70"
      },
      "Health & Wellness": {
        "Text": "Maintain a balanced approach to your well-being.  Prioritize mindful eating and incorporate short periods of relaxation throughout the day to manage stress effectively.  Listen to your body's needs.",
        "percentage": "90"
      },
      "Personal Growth": {
        "Text": "This is a day for expanding your horizons. Embrace new perspectives and engage in activities that stimulate your mind and broaden your understanding of the world.  Learning and self-reflection are highly favored.",
        "percentage": "75"
      }
    },
    "lucky_elements": {
      "lucky_numbers": [
        7,
        11,
        22,
        34,
        45
      ],
      "lucky_colors": [
        "red",
        "deep blue",
        "forest green",
        "golden yellow"
      ]
    },
    "daily_timeline": [
      {
        "time": "6:00 - 8:00",
        "favorability": "neutral",
        "activity": "Morning reflection or light stretching"
      },
      {
        "time": "8:00 - 10:00",
        "favorability": "favorable",
        "activity": "Focus on important communications and planning"
      },
      {
        "time": "10:00 - 12:00",
        "favorability": "most-favorable",
        "activity": "Tackle creative projects or challenging tasks"
      },
      {
        "time": "12:00 - 14:00",
        "favorability": "neutral",
        "activity": "Lunch break, mindful eating, recharge"
      },
      {
        "time": "14:00 - 16:00",
        "favorability": "favorable",
        "activity": "Collaborative work or detail-oriented tasks"
      },
      {
        "time": "16:00 - 18:00",
        "favorability": "favorable",
        "activity": "Networking, learning, or wrapping up work"
      },
      {
        "time": "18:00 - 20:00",
        "favorability": "unfavorable",
        "activity": "Avoid Financial Decisions during this period"
      },
      {
        "time": "20:00 - 22:00",
        "favorability": "neutral",
        "activity": "Relaxation, reading, or preparing for tomorrow"
      }
    ],
    "personalized_recommendations": {
      "dos": [
        "Embrace new perspectives with an open heart.",
        "Practice active listening to foster understanding.",
        "Schedule brief moments for mindfulness throughout the day."
      ],
      "donts": [
        "Avoid snap judgments in complex situations.",
        "Don't let minor setbacks derail your overall progress.",
        "Refrain from overcommitting your time and energy."
      ]
    }
  },
  "Cancer": {
    "Overall": "Cancer, today's planetary alignments encourage introspection and mindful action.  The emotional intensity of the Moon in Scorpio might surface some deep feelings, but the influence of Jupiter in Gemini provides an opportunity for optimistic communication and creative problem-solving.  Trust your intuition, but avoid impulsive decisions, especially concerning finances.",
    "Auspicious Time": "9:00 AM - 10:30 AM",
    "Inauspicious Time": "4:30 PM - 6:00 PM",
    "Daily Wisdom & Suggestions": "Embrace the power of thoughtful communication and find moments of stillness amidst the day's activities to maintain emotional balance.",
    "Detailed Predictions": {
      "Love & Relationships": {
        "Text": "Existing relationships may experience a surge of emotional depth, requiring open and honest communication.  Singles might encounter unexpected connections, but careful consideration is advised before making commitments.",
        "percentage": "75"
      },
      "Career & Money": {
        "Text": "Focus on collaborative projects and detailed tasks.  Avoid major financial decisions today.  Opportunities for professional growth may arise through networking and clear communication.",
        "percentage": "80"
      },
      "Health & Wellness": {
        "Text": "Prioritize mindful eating and relaxation techniques.  The emotional intensity of the day could impact your energy levels.  Engage in activities that promote calmness and inner peace.",
        "percentage": "90"
      },
      "Personal Growth": {
        "Text": "Embrace new perspectives and challenges with an open heart.  This is a day for learning and expanding your understanding of yourself and the world around you.  Mindfulness will be key to personal growth today.",
        "percentage": "70"
      }
    },
    "lucky_elements": {
      "lucky_numbers": [
        7,
        11,
        22,
        34,
        45
      ],
      "lucky_colors": [
        "red",
        "deep blue",
        "forest green",
        "golden yellow"
      ]
    },
    "daily_timeline": [
      {
        "time": "6:00 - 8:00",
        "favorability": "neutral",
        "activity": "Morning reflection or light stretching"
      },
      {
        "time": "8:00 - 10:00",
        "favorability": "favorable",
        "activity": "Focus on important communications and planning"
      },
      {
        "time": "10:00 - 12:00",
        "favorability": "most-favorable",
        "activity": "Tackle creative projects or challenging tasks"
      },
      {
        "time": "12:00 - 14:00",
        "favorability": "neutral",
        "activity": "Lunch break, mindful eating, recharge"
      },
      {
        "time": "14:00 - 16:00",
        "favorability": "favorable",
        "activity": "Collaborative work or detail-oriented tasks"
      },
      {
        "time": "16:00 - 18:00",
        "favorability": "favorable",
        "activity": "Networking, learning, or wrapping up work"
      },
      {
        "time": "18:00 - 20:00",
        "favorability": "unfavorable",
        "activity": "Avoid Financial Decisions during this period"
      },
      {
        "time": "20:00 - 22:00",
        "favorability": "neutral",
        "activity": "Relaxation, reading, or preparing for tomorrow"
      }
    ],
    "personalized_recommendations": {
      "dos": [
        "Embrace new perspectives with an open heart.",
        "Practice active listening to foster understanding.",
        "Schedule brief moments for mindfulness throughout the day."
      ],
      "donts": [
        "Avoid snap judgments in complex situations.",
        "Don't let minor setbacks derail your overall progress.",
        "Refrain from overcommitting your time and energy."
      ]
    }
  },
  "Leo": {
    "Overall": "Leo, today's planetary alignment brings a vibrant energy, fueled by Mars in your sign.  Expect a surge in confidence and creativity, but temper your impulsive nature with mindful planning.  The Gemini Sun and Jupiter encourage communication and expansion, while the Scorpio Moon adds emotional depth.  Use this powerful energy wisely.",
    "Auspicious Time": "11:00 AM - 1:00 PM",
    "Inauspicious Time": "6:00 PM - 7:30 PM",
    "Daily Wisdom & Suggestions": "Embrace the power of your inner strength, and remember that patience is key to unlocking your true potential.",
    "Detailed Predictions": {
      "Love & Relationships": {
        "Text": "Your passionate nature shines brightly today, Leo.  Open communication and a willingness to compromise will strengthen existing bonds. Singles might encounter a charismatic individual, but proceed cautiously.",
        "percentage": "85"
      },
      "Career & Money": {
        "Text": "Your drive and ambition are rewarded today, Leo.  Focus on collaborative projects and networking opportunities.  Avoid making significant financial decisions during the late afternoon.",
        "percentage": "78"
      },
      "Health & Wellness": {
        "Text": "Maintain a balanced approach to your well-being.  The intense energy may lead to restlessness, so prioritize mindfulness and relaxation techniques.  Sufficient rest is crucial.",
        "percentage": "90"
      },
      "Personal Growth": {
        "Text": "Today is ideal for pursuing creative endeavors and tackling challenging tasks.  Embrace new perspectives and learn from any setbacks.  Your personal growth is accelerated by your proactive approach.",
        "percentage": "75"
      }
    },
    "lucky_elements": {
      "lucky_numbers": [
        7,
        11,
        22,
        34,
        45
      ],
      "lucky_colors": [
        "red",
        "deep blue",
        "forest green",
        "golden yellow"
      ]
    },
    "daily_timeline": [
      {
        "time": "6:00 - 8:00",
        "favorability": "neutral",
        "activity": "Morning reflection or light stretching"
      },
      {
        "time": "8:00 - 10:00",
        "favorability": "favorable",
        "activity": "Focus on important communications and planning"
      },
      {
        "time": "10:00 - 12:00",
        "favorability": "most-favorable",
        "activity": "Tackle creative projects or challenging tasks"
      },
      {
        "time": "12:00 - 14:00",
        "favorability": "neutral",
        "activity": "Lunch break, mindful eating, recharge"
      },
      {
        "time": "14:00 - 16:00",
        "favorability": "favorable",
        "activity": "Collaborative work or detail-oriented tasks"
      },
      {
        "time": "16:00 - 18:00",
        "favorability": "favorable",
        "activity": "Networking, learning, or wrapping up work"
      },
      {
        "time": "18:00 - 20:00",
        "favorability": "unfavorable",
        "activity": "Avoid Financial Decisions during this period"
      },
      {
        "time": "20:00 - 22:00",
        "favorability": "neutral",
        "activity": "Relaxation, reading, or preparing for tomorrow"
      }
    ],
    "personalized_recommendations": {
      "dos": [
        "Embrace new perspectives with an open heart.",
        "Practice active listening to foster understanding.",
        "Schedule brief moments for mindfulness throughout the day."
      ],
      "donts": [
        "Avoid snap judgments in complex situations.",
        "Don't let minor setbacks derail your overall progress.",
        "Refrain from overcommitting your time and energy."
      ]
    }
  },
  "Virgo": {
    "Overall": "Virgo, today's planetary alignments encourage a blend of meticulous planning and creative expression.  The Sun, Mercury, and Jupiter in Gemini amplify your communication skills, while the Moon in Scorpio adds intensity to your emotions.  Use this energy wisely to achieve balance between your analytical nature and your intuitive insights.",
    "Auspicious Time": "9:00 AM - 10:30 AM",
    "Inauspicious Time": "4:30 PM - 6:00 PM",
    "Daily Wisdom & Suggestions": "Embrace calculated risks while maintaining a grounded approach. Listen to your intuition, but verify your insights with logical analysis.",
    "Detailed Predictions": {
      "Love & Relationships": {
        "Text": "Existing relationships may benefit from open communication and a renewed appreciation for shared experiences.  Singles might encounter unexpected connections, but cautious observation is advised before making significant commitments.",
        "percentage": "70"
      },
      "Career & Money": {
        "Text": "Focus on detailed work and strategic planning.  Avoid impulsive financial decisions.  Opportunities for advancement may arise if you demonstrate your meticulous skills and attention to detail.",
        "percentage": "80"
      },
      "Health & Wellness": {
        "Text": "Prioritize mindful practices to manage stress effectively.  Pay attention to your body's signals and ensure adequate rest.  A balanced diet and regular exercise will support your overall well-being.",
        "percentage": "85"
      },
      "Personal Growth": {
        "Text": "Engage in activities that stimulate your intellectual curiosity and expand your knowledge.  Embrace new perspectives and challenges to foster personal growth and self-discovery.  Reflect on your values and aspirations.",
        "percentage": "75"
      }
    },
    "lucky_elements": {
      "lucky_numbers": [
        7,
        11,
        22,
        34,
        45
      ],
      "lucky_colors": [
        "red",
        "deep blue",
        "forest green",
        "golden yellow"
      ]
    },
    "daily_timeline": [
      {
        "time": "6:00 - 8:00",
        "favorability": "neutral",
        "activity": "Morning reflection or light stretching"
      },
      {
        "time": "8:00 - 10:00",
        "favorability": "favorable",
        "activity": "Focus on important communications and planning"
      },
      {
        "time": "10:00 - 12:00",
        "favorability": "most-favorable",
        "activity": "Tackle creative projects or challenging tasks"
      },
      {
        "time": "12:00 - 14:00",
        "favorability": "neutral",
        "activity": "Lunch break, mindful eating, recharge"
      },
      {
        "time": "14:00 - 16:00",
        "favorability": "favorable",
        "activity": "Collaborative work or detail-oriented tasks"
      },
      {
        "time": "16:00 - 18:00",
        "favorability": "favorable",
        "activity": "Networking, learning, or wrapping up work"
      },
      {
        "time": "18:00 - 20:00",
        "favorability": "unfavorable",
        "activity": "Avoid Financial Decisions during this period"
      },
      {
        "time": "20:00 - 22:00",
        "favorability": "neutral",
        "activity": "Relaxation, reading, or preparing for tomorrow"
      }
    ],
    "personalized_recommendations": {
      "dos": [
        "Embrace new perspectives with an open heart.",
        "Practice active listening to foster understanding.",
        "Schedule brief moments for mindfulness throughout the day."
      ],
      "donts": [
        "Avoid snap judgments in complex situations.",
        "Don't let minor setbacks derail your overall progress.",
        "Refrain from overcommitting your time and energy."
      ]
    }
  },
  "Libra": {
    "Overall": "Libra, today's planetary alignments suggest a day of balanced energy.  The Sun and Jupiter in Gemini encourage communication and expansion, while the Moon in Scorpio adds depth and intensity to your emotions.  Use this blend to your advantage, focusing on clear expression and strategic planning.",
    "Auspicious Time": "9:00 AM - 10:30 AM",
    "Inauspicious Time": "4:30 PM - 6:00 PM",
    "Daily Wisdom & Suggestions": "Embrace new perspectives while avoiding snap judgments; mindful moments can help navigate complex situations with grace.",
    "Detailed Predictions": {
      "Love & Relationships": {
        "Text": "Existing relationships will benefit from open and honest communication. Singles may encounter someone intriguing, but patience is key. Prioritize emotional connection over superficial attraction.",
        "percentage": "80"
      },
      "Career & Money": {
        "Text": "Focus on collaboration and clear communication at work.  Financial decisions should be postponed until after the inauspicious time. Opportunities for growth may present themselves through networking.",
        "percentage": "75"
      },
      "Health & Wellness": {
        "Text": "Prioritize mindful eating and gentle exercise. The Scorpio Moon may heighten emotional sensitivity, so practice self-care and stress management techniques.  Plenty of rest is recommended.",
        "percentage": "85"
      },
      "Personal Growth": {
        "Text": "Embrace new learning experiences and expand your horizons.  Challenge yourself creatively, but avoid overcommitting your time and energy.  Focus on sustainable personal growth.",
        "percentage": "70"
      }
    },
    "lucky_elements": {
      "lucky_numbers": [
        7,
        11,
        22,
        34,
        45
      ],
      "lucky_colors": [
        "red",
        "deep blue",
        "forest green",
        "golden yellow"
      ]
    },
    "daily_timeline": [
      {
        "time": "6:00 - 8:00",
        "favorability": "neutral",
        "activity": "Morning reflection or light stretching"
      },
      {
        "time": "8:00 - 10:00",
        "favorability": "favorable",
        "activity": "Focus on important communications and planning"
      },
      {
        "time": "10:00 - 12:00",
        "favorability": "most-favorable",
        "activity": "Tackle creative projects or challenging tasks"
      },
      {
        "time": "12:00 - 14:00",
        "favorability": "neutral",
        "activity": "Lunch break, mindful eating, recharge"
      },
      {
        "time": "14:00 - 16:00",
        "favorability": "favorable",
        "activity": "Collaborative work or detail-oriented tasks"
      },
      {
        "time": "16:00 - 18:00",
        "favorability": "favorable",
        "activity": "Networking, learning, or wrapping up work"
      },
      {
        "time": "18:00 - 20:00",
        "favorability": "unfavorable",
        "activity": "Avoid Financial Decisions during this period"
      },
      {
        "time": "20:00 - 22:00",
        "favorability": "neutral",
        "activity": "Relaxation, reading, or preparing for tomorrow"
      }
    ],
    "personalized_recommendations": {
      "dos": [
        "Embrace new perspectives with an open heart.",
        "Practice active listening to foster understanding.",
        "Schedule brief moments for mindfulness throughout the day."
      ],
      "donts": [
        "Avoid snap judgments in complex situations.",
        "Don't let minor setbacks derail your overall progress.",
        "Refrain from overcommitting your time and energy."
      ]
    }
  },
  "Scorpio": {
    "Overall": "Scorpio, today's powerful lunar influence in your sign amplifies your intensity and intuition.  With Mercury and Jupiter in Gemini, communication is key, but avoid impulsive reactions. Harness your emotional depth to navigate complex situations with grace and clarity.  The alignment of planets encourages introspection and decisive action.",
    "Auspicious Time": "9:00 AM - 10:30 AM",
    "Inauspicious Time": "4:30 PM - 6:00 PM",
    "Daily Wisdom & Suggestions": "Embrace your inner strength and trust your instincts, but temper your passionate nature with thoughtful consideration before making significant decisions.",
    "Detailed Predictions": {
      "Love & Relationships": {
        "Text": "Existing relationships may experience heightened emotional intensity.  Single Scorpios might find themselves drawn to someone unexpected.  Communication is crucial to navigating any potential misunderstandings.",
        "percentage": "85"
      },
      "Career & Money": {
        "Text": "Your sharp mind and determined nature will serve you well in professional endeavors.  Opportunities for advancement may arise, but carefully weigh the risks before committing to new ventures.  Avoid major financial decisions during the inauspicious time.",
        "percentage": "70"
      },
      "Health & Wellness": {
        "Text": "Pay attention to your physical and mental well-being.  The lunar influence might amplify stress; prioritize relaxation techniques and mindful practices.  Ensure you're getting enough rest and nourishment.",
        "percentage": "90"
      },
      "Personal Growth": {
        "Text": "Today presents a chance for significant personal growth.  Embrace challenges as opportunities for learning and self-discovery.  Reflect on your goals and make adjustments as needed.",
        "percentage": "75"
      }
    },
    "lucky_elements": {
      "lucky_numbers": [
        7,
        11,
        22,
        34,
        45
      ],
      "lucky_colors": [
        "red",
        "deep blue",
        "forest green",
        "golden yellow"
      ]
    },
    "daily_timeline": [
      {
        "time": "6:00 - 8:00",
        "favorability": "neutral",
        "activity": "Morning reflection or light stretching"
      },
      {
        "time": "8:00 - 10:00",
        "favorability": "favorable",
        "activity": "Focus on important communications and planning"
      },
      {
        "time": "10:00 - 12:00",
        "favorability": "most-favorable",
        "activity": "Tackle creative projects or challenging tasks"
      },
      {
        "time": "12:00 - 14:00",
        "favorability": "neutral",
        "activity": "Lunch break, mindful eating, recharge"
      },
      {
        "time": "14:00 - 16:00",
        "favorability": "favorable",
        "activity": "Collaborative work or detail-oriented tasks"
      },
      {
        "time": "16:00 - 18:00",
        "favorability": "favorable",
        "activity": "Networking, learning, or wrapping up work"
      },
      {
        "time": "18:00 - 20:00",
        "favorability": "unfavorable",
        "activity": "Avoid Financial Decisions during this period"
      },
      {
        "time": "20:00 - 22:00",
        "favorability": "neutral",
        "activity": "Relaxation, reading, or preparing for tomorrow"
      }
    ],
    "personalized_recommendations": {
      "dos": [
        "Embrace new perspectives with an open heart.",
        "Practice active listening to foster understanding.",
        "Schedule brief moments for mindfulness throughout the day."
      ],
      "donts": [
        "Avoid snap judgments in complex situations.",
        "Don't let minor setbacks derail your overall progress.",
        "Refrain from overcommitting your time and energy."
      ]
    }
  },
  "Sagittarius": {
    "Overall": "Sagittarius, today's planetary alignment encourages you to embrace your adventurous spirit while maintaining a grounded approach.  The influence of Jupiter in Gemini enhances your communication skills, making it an ideal day for collaborations and creative pursuits. However, the Scorpio moon might bring emotional intensity, so mindful self-reflection is key.",
    "Auspicious Time": "9:00 AM - 10:30 AM",
    "Inauspicious Time": "4:30 PM - 6:00 PM",
    "Daily Wisdom & Suggestions": "Listen intently to both your inner voice and the perspectives of others; this balance will guide you towards wise decisions and fulfilling interactions.",
    "Detailed Predictions": {
      "Love & Relationships": {
        "Text": "Singles might encounter unexpected romantic opportunities. Committed Sagittarians should prioritize open communication to strengthen their bond.  Focus on mutual understanding and appreciation.",
        "percentage": "85"
      },
      "Career & Money": {
        "Text": "Your creative energy is high, making it a productive day for brainstorming and project development.  Avoid impulsive financial decisions; careful planning is advised.",
        "percentage": "70"
      },
      "Health & Wellness": {
        "Text": "Prioritize mindful movement and relaxation techniques.  The emotional intensity of the day might lead to stress; ensure you take time for self-care.",
        "percentage": "90"
      },
      "Personal Growth": {
        "Text": "Embrace new learning experiences and broaden your horizons.  This is a time for intellectual stimulation and expanding your perspectives. Trust your intuition.",
        "percentage": "75"
      }
    },
    "lucky_elements": {
      "lucky_numbers": [
        7,
        11,
        22,
        34,
        45
      ],
      "lucky_colors": [
        "red",
        "deep blue",
        "forest green",
        "golden yellow"
      ]
    },
    "daily_timeline": [
      {
        "time": "6:00 - 8:00",
        "favorability": "neutral",
        "activity": "Morning reflection or light stretching"
      },
      {
        "time": "8:00 - 10:00",
        "favorability": "favorable",
        "activity": "Focus on important communications and planning"
      },
      {
        "time": "10:00 - 12:00",
        "favorability": "most-favorable",
        "activity": "Tackle creative projects or challenging tasks"
      },
      {
        "time": "12:00 - 14:00",
        "favorability": "neutral",
        "activity": "Lunch break, mindful eating, recharge"
      },
      {
        "time": "14:00 - 16:00",
        "favorability": "favorable",
        "activity": "Collaborative work or detail-oriented tasks"
      },
      {
        "time": "16:00 - 18:00",
        "favorability": "favorable",
        "activity": "Networking, learning, or wrapping up work"
      },
      {
        "time": "18:00 - 20:00",
        "favorability": "unfavorable",
        "activity": "Avoid Financial Decisions during this period"
      },
      {
        "time": "20:00 - 22:00",
        "favorability": "neutral",
        "activity": "Relaxation, reading, or preparing for tomorrow"
      }
    ],
    "personalized_recommendations": {
      "dos": [
        "Embrace new perspectives with an open heart.",
        "Practice active listening to foster understanding.",
        "Schedule brief moments for mindfulness throughout the day."
      ],
      "donts": [
        "Avoid snap judgments in complex situations.",
        "Don't let minor setbacks derail your overall progress.",
        "Refrain from overcommitting your time and energy."
      ]
    }
  },
  "Capricorn": {
    "Overall": "Capricorn, today's planetary alignment encourages a balanced approach.  The Sun and Jupiter in Gemini highlight communication and expansion, while the Moon in Scorpio adds intensity to your emotions. Saturn in Aries pushes you to take initiative, but avoid impulsive decisions.  Harness your ambition wisely, focusing on practical steps.",
    "Auspicious Time": "9:00 AM - 10:30 AM",
    "Inauspicious Time": "4:30 PM - 6:00 PM",
    "Daily Wisdom & Suggestions": "Embrace calculated risks, but prioritize mindful action over impulsive reactions.  Listen to your intuition, but ground your decisions in practicality and foresight.",
    "Detailed Predictions": {
      "Love & Relationships": {
        "Text": "Existing relationships may experience a surge of passion and deeper understanding.  Singles might encounter unexpected connections, but take your time before making commitments. Prioritize open communication.",
        "percentage": "80"
      },
      "Career & Money": {
        "Text": "Focus on collaborative efforts and strategic planning to advance your career.  Avoid major financial decisions today.  Opportunities for growth are present, but careful consideration is crucial.",
        "percentage": "75"
      },
      "Health & Wellness": {
        "Text": "Prioritize mindful self-care.  The intense energy of the day could lead to stress; incorporate relaxation techniques into your routine.  Maintain a balanced diet and get sufficient rest.",
        "percentage": "85"
      },
      "Personal Growth": {
        "Text": "Today is ideal for tackling challenging projects and expanding your knowledge.  Embrace new perspectives and be open to learning.  Your personal growth hinges on your willingness to adapt.",
        "percentage": "70"
      }
    },
    "lucky_elements": {
      "lucky_numbers": [
        7,
        11,
        22,
        34,
        45
      ],
      "lucky_colors": [
        "red",
        "deep blue",
        "forest green",
        "golden yellow"
      ]
    },
    "daily_timeline": [
      {
        "time": "6:00 - 8:00",
        "favorability": "neutral",
        "activity": "Morning reflection or light stretching"
      },
      {
        "time": "8:00 - 10:00",
        "favorability": "favorable",
        "activity": "Focus on important communications and planning"
      },
      {
        "time": "10:00 - 12:00",
        "favorability": "most-favorable",
        "activity": "Tackle creative projects or challenging tasks"
      },
      {
        "time": "12:00 - 14:00",
        "favorability": "neutral",
        "activity": "Lunch break, mindful eating, recharge"
      },
      {
        "time": "14:00 - 16:00",
        "favorability": "favorable",
        "activity": "Collaborative work or detail-oriented tasks"
      },
      {
        "time": "16:00 - 18:00",
        "favorability": "favorable",
        "activity": "Networking, learning, or wrapping up work"
      },
      {
        "time": "18:00 - 20:00",
        "favorability": "unfavorable",
        "activity": "Avoid Financial Decisions during this period"
      },
      {
        "time": "20:00 - 22:00",
        "favorability": "neutral",
        "activity": "Relaxation, reading, or preparing for tomorrow"
      }
    ],
    "personalized_recommendations": {
      "dos": [
        "Embrace new perspectives with an open heart.",
        "Practice active listening to foster understanding.",
        "Schedule brief moments for mindfulness throughout the day."
      ],
      "donts": [
        "Avoid snap judgments in complex situations.",
        "Don't let minor setbacks derail your overall progress.",
        "Refrain from overcommitting your time and energy."
      ]
    }
  },
  "Aquarius": {
    "Overall": "Aquarius, today's planetary alignments bring a blend of intellectual stimulation and emotional intensity.  The presence of Pluto in your sign encourages deep introspection, while the Sun and Mercury in Gemini urge you to communicate your thoughts clearly.  Expect a day of dynamic energy, requiring careful management of your time and resources.",
    "Auspicious Time": "11:00 AM - 1:00 PM",
    "Inauspicious Time": "5:00 PM - 7:00 PM",
    "Daily Wisdom & Suggestions": "Embrace change with an open mind, and remember that even small acts of self-care can have a profound impact on your well-being.",
    "Detailed Predictions": {
      "Love & Relationships": {
        "Text": "Existing relationships may require open communication to navigate potential misunderstandings. Singles might find themselves drawn to someone unexpected, igniting a spark of intrigue.  Focus on honesty and genuine connection.",
        "percentage": "70"
      },
      "Career & Money": {
        "Text": "A collaborative project could lead to significant professional growth.  However, avoid impulsive financial decisions; careful planning is key to long-term financial security.  Review contracts thoroughly.",
        "percentage": "80"
      },
      "Health & Wellness": {
        "Text": "Prioritize self-care; incorporate mindfulness exercises into your daily routine to manage stress effectively.  Pay attention to your body's signals and ensure adequate rest.  A healthy diet will boost your energy.",
        "percentage": "90"
      },
      "Personal Growth": {
        "Text": "Today presents an excellent opportunity for personal growth through introspection and learning.  Embrace new perspectives and challenge your assumptions.  Seek out opportunities for intellectual stimulation.",
        "percentage": "75"
      }
    },
    "lucky_elements": {
      "lucky_numbers": [
        7,
        11,
        22,
        34,
        45
      ],
      "lucky_colors": [
        "red",
        "deep blue",
        "forest green",
        "golden yellow"
      ]
    },
    "daily_timeline": [
      {
        "time": "6:00 - 8:00",
        "favorability": "neutral",
        "activity": "Morning reflection or light stretching"
      },
      {
        "time": "8:00 - 10:00",
        "favorability": "favorable",
        "activity": "Focus on important communications and planning"
      },
      {
        "time": "10:00 - 12:00",
        "favorability": "most-favorable",
        "activity": "Tackle creative projects or challenging tasks"
      },
      {
        "time": "12:00 - 14:00",
        "favorability": "neutral",
        "activity": "Lunch break, mindful eating, recharge"
      },
      {
        "time": "14:00 - 16:00",
        "favorability": "favorable",
        "activity": "Collaborative work or detail-oriented tasks"
      },
      {
        "time": "16:00 - 18:00",
        "favorability": "favorable",
        "activity": "Networking, learning, or wrapping up work"
      },
      {
        "time": "18:00 - 20:00",
        "favorability": "unfavorable",
        "activity": "Avoid Financial Decisions during this period"
      },
      {
        "time": "20:00 - 22:00",
        "favorability": "neutral",
        "activity": "Relaxation, reading, or preparing for tomorrow"
      }
    ],
    "personalized_recommendations": {
      "dos": [
        "Embrace new perspectives with an open heart.",
        "Practice active listening to foster understanding.",
        "Schedule brief moments for mindfulness throughout the day."
      ],
      "donts": [
        "Avoid snap judgments in complex situations.",
        "Don't let minor setbacks derail your overall progress.",
        "Refrain from overcommitting your time and energy."
      ]
    }
  },
  "Pisces": {
    "Overall": "Pisces, today's planetary alignment encourages introspection and mindful action.  The influence of the Moon in Scorpio heightens your intuition, while Gemini's energy promotes communication and adaptability.  Use this blend to navigate challenges with grace and creativity.",
    "Auspicious Time": "9:00 AM - 11:00 AM",
    "Inauspicious Time": "3:00 PM - 5:00 PM",
    "Daily Wisdom & Suggestions": "Trust your instincts and communicate your needs clearly.  Avoid impulsive decisions and prioritize self-care.",
    "Detailed Predictions": {
      "Love & Relationships": {
        "Text": "Existing relationships may require open communication to address any underlying tensions.  Singles should focus on self-love and personal growth before seeking a new connection.  Trust your intuition in matters of the heart.",
        "percentage": "70"
      },
      "Career & Money": {
        "Text": "Focus on collaborative projects and detailed tasks. Avoid making significant financial decisions today; instead, concentrate on planning and strategizing for future opportunities.  A cautious approach is advised.",
        "percentage": "65"
      },
      "Health & Wellness": {
        "Text": "Prioritize rest and relaxation.  Engage in activities that nurture your mind and body, such as meditation or gentle exercise.  Pay attention to your emotional well-being and address any stress proactively.",
        "percentage": "80"
      },
      "Personal Growth": {
        "Text": "Embrace new learning opportunities and broaden your horizons.  This is a day for expanding your knowledge and perspective, leading to significant personal growth. Trust your intuition to guide you.",
        "percentage": "75"
      }
    },
    "lucky_elements": {
      "lucky_numbers": [
        7,
        11,
        22,
        34,
        45
      ],
      "lucky_colors": [
        "red",
        "deep blue",
        "forest green",
        "golden yellow"
      ]
    },
    "daily_timeline": [
      {
        "time": "6:00 - 8:00",
        "favorability": "neutral",
        "activity": "Morning reflection or light stretching"
      },
      {
        "time": "8:00 - 10:00",
        "favorability": "favorable",
        "activity": "Focus on important communications and planning"
      },
      {
        "time": "10:00 - 12:00",
        "favorability": "most-favorable",
        "activity": "Tackle creative projects or challenging tasks"
      },
      {
        "time": "12:00 - 14:00",
        "favorability": "neutral",
        "activity": "Lunch break, mindful eating, recharge"
      },
      {
        "time": "14:00 - 16:00",
        "favorability": "favorable",
        "activity": "Collaborative work or detail-oriented tasks"
      },
      {
        "time": "16:00 - 18:00",
        "favorability": "favorable",
        "activity": "Networking, learning, or wrapping up work"
      },
      {
        "time": "18:00 - 20:00",
        "favorability": "unfavorable",
        "activity": "Avoid Financial Decisions during this period"
      },
      {
        "time": "20:00 - 22:00",
        "favorability": "neutral",
        "activity": "Relaxation, reading, or preparing for tomorrow"
      }
    ],
    "personalized_recommendations": {
      "dos": [
        "Embrace new perspectives with an open heart.",
        "Practice active listening to foster understanding.",
        "Schedule brief moments for mindfulness throughout the day."
      ],
      "donts": [
        "Avoid snap judgments in complex situations.",
        "Don't let minor setbacks derail your overall progress.",
        "Refrain from overcommitting your time and energy."
      ]
    }
  }
}