{
  "Aries": {
    "Overall": "Aries, today's planetary alignment brings a potent mix of energy and introspection.  Venus in your sign fuels your charisma and passion, while Saturn's presence demands discipline and focus.  Use this potent combination to achieve significant progress, but remember to pace yourself and avoid impulsive decisions.",
    "Auspicious Time": "9:00 AM - 10:30 AM",
    "Inauspicious Time": "4:30 PM - 6:00 PM",
    "Daily Wisdom & Suggestions": "Embrace your inner strength and resilience while remaining open to new perspectives; cultivate mindful awareness to navigate challenges with grace and clarity.",
    "Detailed Predictions": {
      "Love & Relationships": {
        "Text": "Your passionate nature shines brightly today, Aries.  Existing relationships will benefit from open communication and shared experiences.  Singles might encounter a surprising connection.",
        "percentage": "85"
      },
      "Career & Money": {
        "Text": "Your hard work and dedication are paying off.  Focus on completing tasks meticulously, and don't hesitate to seek assistance when needed.  Avoid major financial decisions during the inauspicious time.",
        "percentage": "78"
      },
      "Health & Wellness": {
        "Text": "Prioritize self-care today, Aries.  The current planetary influences may leave you feeling slightly drained.  Engage in relaxing activities and ensure you get enough rest.",
        "percentage": "90"
      },
      "Personal Growth": {
        "Text": "Embrace new challenges with enthusiasm, Aries.  Your ability to learn and adapt is highlighted today.  Use this opportunity for self-improvement and expansion.",
        "percentage": "75"
      }
    },
    "lucky_elements": {
      "lucky_numbers": [
        7,
        11,
        22,
        34,
        45
      ],
      "lucky_colors": [
        "red",
        "deep blue",
        "forest green",
        "golden yellow"
      ]
    },
    "daily_timeline": [
      {
        "time": "6:00 - 8:00",
        "favorability": "neutral",
        "activity": "Morning reflection or light stretching"
      },
      {
        "time": "8:00 - 10:00",
        "favorability": "favorable",
        "activity": "Focus on important communications and planning"
      },
      {
        "time": "10:00 - 12:00",
        "favorability": "most-favorable",
        "activity": "Tackle creative projects or challenging tasks"
      },
      {
        "time": "12:00 - 14:00",
        "favorability": "neutral",
        "activity": "Lunch break, mindful eating, recharge"
      },
      {
        "time": "14:00 - 16:00",
        "favorability": "favorable",
        "activity": "Collaborative work or detail-oriented tasks"
      },
      {
        "time": "16:00 - 18:00",
        "favorability": "favorable",
        "activity": "Networking, learning, or wrapping up work"
      },
      {
        "time": "18:00 - 20:00",
        "favorability": "unfavorable",
        "activity": "Avoid Financial Decisions during this period"
      },
      {
        "time": "20:00 - 22:00",
        "favorability": "neutral",
        "activity": "Relaxation, reading, or preparing for tomorrow"
      }
    ],
    "personalized_recommendations": {
      "dos": [
        "Embrace new perspectives with an open heart.",
        "Practice active listening to foster understanding.",
        "Schedule brief moments for mindfulness throughout the day."
      ],
      "donts": [
        "Avoid snap judgments in complex situations.",
        "Don't let minor setbacks derail your overall progress.",
        "Refrain from overcommitting your time and energy."
      ]
    }
  },
  "Taurus": {
    "Overall": "Taurus, today's planetary alignments encourage a balanced approach.  The Sun and Jupiter in Gemini stimulate your mind, prompting insightful communication. However, Uranus in your sign urges you to be mindful of impulsive reactions.  Harness your grounded nature to navigate the day's energetic shifts.",
    "Auspicious Time": "9:00 AM - 10:30 AM",
    "Inauspicious Time": "4:30 PM - 6:00 PM",
    "Daily Wisdom & Suggestions": "Embrace patience in the face of challenges and remember that true progress requires consistent effort, not frantic rushing.",
    "Detailed Predictions": {
      "Love & Relationships": {
        "Text": "Existing relationships may experience a surge of passion and intimacy. For singles, be open to unexpected connections; a chance encounter could lead to something meaningful.  Communication is key to navigating any misunderstandings.",
        "percentage": "85"
      },
      "Career & Money": {
        "Text": "Your hard work is likely to be recognized, leading to potential advancements or increased financial rewards.  Focus on collaborative projects and avoid risky investments during the inauspicious time.",
        "percentage": "78"
      },
      "Health & Wellness": {
        "Text": "Prioritize self-care; incorporate mindfulness and light exercise into your routine.  Pay attention to your diet and ensure sufficient rest to maintain energy levels.  Avoid overexertion.",
        "percentage": "90"
      },
      "Personal Growth": {
        "Text": "Embrace new learning opportunities and expand your horizons.  Today is ideal for tackling creative projects or engaging in activities that stimulate intellectual curiosity. Step outside your comfort zone.",
        "percentage": "75"
      }
    },
    "lucky_elements": {
      "lucky_numbers": [
        7,
        11,
        22,
        34,
        45
      ],
      "lucky_colors": [
        "red",
        "deep blue",
        "forest green",
        "golden yellow"
      ]
    },
    "daily_timeline": [
      {
        "time": "6:00 - 8:00",
        "favorability": "neutral",
        "activity": "Morning reflection or light stretching"
      },
      {
        "time": "8:00 - 10:00",
        "favorability": "favorable",
        "activity": "Focus on important communications and planning"
      },
      {
        "time": "10:00 - 12:00",
        "favorability": "most-favorable",
        "activity": "Tackle creative projects or challenging tasks"
      },
      {
        "time": "12:00 - 14:00",
        "favorability": "neutral",
        "activity": "Lunch break, mindful eating, recharge"
      },
      {
        "time": "14:00 - 16:00",
        "favorability": "favorable",
        "activity": "Collaborative work or detail-oriented tasks"
      },
      {
        "time": "16:00 - 18:00",
        "favorability": "favorable",
        "activity": "Networking, learning, or wrapping up work"
      },
      {
        "time": "18:00 - 20:00",
        "favorability": "unfavorable",
        "activity": "Avoid Financial Decisions during this period"
      },
      {
        "time": "20:00 - 22:00",
        "favorability": "neutral",
        "activity": "Relaxation, reading, or preparing for tomorrow"
      }
    ],
    "personalized_recommendations": {
      "dos": [
        "Embrace new perspectives with an open heart.",
        "Practice active listening to foster understanding.",
        "Schedule brief moments for mindfulness throughout the day."
      ],
      "donts": [
        "Avoid snap judgments in complex situations.",
        "Don't let minor setbacks derail your overall progress.",
        "Refrain from overcommitting your time and energy."
      ]
    }
  },
  "Gemini": {
    "Overall": "Gemini, the planetary alignment today emphasizes communication and creativity.  With the Sun, Mercury, and Jupiter all in your sign, your mental agility is heightened.  However, the influence of Mars in Leo might lead to impulsive actions, so mindful self-control is key.  Channel your energy wisely to achieve significant progress.",
    "Auspicious Time": "9:00 AM - 10:30 AM",
    "Inauspicious Time": "4:30 PM - 6:00 PM",
    "Daily Wisdom & Suggestions": "Embrace your inherent adaptability and focus on clear communication to navigate any challenges that arise. Remember that thoughtful planning and patience will yield greater rewards than impulsive action.",
    "Detailed Predictions": {
      "Love & Relationships": {
        "Text": "Existing relationships benefit from open and honest communication today.  Singles might encounter unexpected connections, but avoid rushing into commitments.  Focus on building genuine rapport.",
        "percentage": "80"
      },
      "Career & Money": {
        "Text": "Your sharp intellect and communication skills are assets in your professional life today.  New opportunities may arise, but carefully evaluate them before committing.  Avoid major financial decisions during the inauspicious time.",
        "percentage": "75"
      },
      "Health & Wellness": {
        "Text": "Prioritize mindful eating and incorporate light exercise into your day.  The influence of Virgo Moon encourages a focus on well-being.  Stress management techniques are particularly beneficial.",
        "percentage": "85"
      },
      "Personal Growth": {
        "Text": "Today is ideal for pursuing creative projects or learning something new.  Embrace challenges as opportunities for growth.  Reflect on your progress and celebrate your achievements.",
        "percentage": "70"
      }
    },
    "lucky_elements": {
      "lucky_numbers": [
        7,
        11,
        22,
        34,
        45
      ],
      "lucky_colors": [
        "red",
        "deep blue",
        "forest green",
        "golden yellow"
      ]
    },
    "daily_timeline": [
      {
        "time": "6:00 - 8:00",
        "favorability": "neutral",
        "activity": "Morning reflection or light stretching"
      },
      {
        "time": "8:00 - 10:00",
        "favorability": "favorable",
        "activity": "Focus on important communications and planning"
      },
      {
        "time": "10:00 - 12:00",
        "favorability": "most-favorable",
        "activity": "Tackle creative projects or challenging tasks"
      },
      {
        "time": "12:00 - 14:00",
        "favorability": "neutral",
        "activity": "Lunch break, mindful eating, recharge"
      },
      {
        "time": "14:00 - 16:00",
        "favorability": "favorable",
        "activity": "Collaborative work or detail-oriented tasks"
      },
      {
        "time": "16:00 - 18:00",
        "favorability": "favorable",
        "activity": "Networking, learning, or wrapping up work"
      },
      {
        "time": "18:00 - 20:00",
        "favorability": "unfavorable",
        "activity": "Avoid Financial Decisions during this period"
      },
      {
        "time": "20:00 - 22:00",
        "favorability": "neutral",
        "activity": "Relaxation, reading, or preparing for tomorrow"
      }
    ],
    "personalized_recommendations": {
      "dos": [
        "Embrace new perspectives with an open heart.",
        "Practice active listening to foster understanding.",
        "Schedule brief moments for mindfulness throughout the day."
      ],
      "donts": [
        "Avoid snap judgments in complex situations.",
        "Don't let minor setbacks derail your overall progress.",
        "Refrain from overcommitting your time and energy."
      ]
    }
  },
  "Cancer": {
    "Overall": "Cancer, today's planetary alignments encourage introspection and mindful action.  The influence of Mercury and Jupiter in Gemini sharpens your communication skills, while the Moon in Virgo grounds you in practicality.  However, be wary of impulsiveness; thoughtful consideration will lead to better outcomes.",
    "Auspicious Time": "9:00 AM - 10:30 AM",
    "Inauspicious Time": "4:30 PM - 6:00 PM",
    "Daily Wisdom & Suggestions": "Listen to your intuition and trust your gut feelings, but always balance that with logical reasoning and careful planning for the best results.",
    "Detailed Predictions": {
      "Love & Relationships": {
        "Text": "Existing relationships may benefit from open communication and a renewed appreciation for each other. Singles should focus on self-care and personal growth before seeking new connections.",
        "percentage": "75"
      },
      "Career & Money": {
        "Text": "Focus on meticulous work and clear communication to avoid misunderstandings.  Avoid major financial decisions today, as the planetary influences may cloud your judgment.",
        "percentage": "65"
      },
      "Health & Wellness": {
        "Text": "Prioritize rest and relaxation.  Engage in calming activities like yoga or meditation to reduce stress and enhance your well-being.  Mindful eating will aid digestion.",
        "percentage": "80"
      },
      "Personal Growth": {
        "Text": "Embrace opportunities for learning and self-improvement.  Reflect on your goals and identify areas where you can make positive changes.  Today is ideal for creative pursuits.",
        "percentage": "78"
      }
    },
    "lucky_elements": {
      "lucky_numbers": [
        7,
        11,
        22,
        34,
        45
      ],
      "lucky_colors": [
        "red",
        "deep blue",
        "forest green",
        "golden yellow"
      ]
    },
    "daily_timeline": [
      {
        "time": "6:00 - 8:00",
        "favorability": "neutral",
        "activity": "Morning reflection or light stretching"
      },
      {
        "time": "8:00 - 10:00",
        "favorability": "favorable",
        "activity": "Focus on important communications and planning"
      },
      {
        "time": "10:00 - 12:00",
        "favorability": "most-favorable",
        "activity": "Tackle creative projects or challenging tasks"
      },
      {
        "time": "12:00 - 14:00",
        "favorability": "neutral",
        "activity": "Lunch break, mindful eating, recharge"
      },
      {
        "time": "14:00 - 16:00",
        "favorability": "favorable",
        "activity": "Collaborative work or detail-oriented tasks"
      },
      {
        "time": "16:00 - 18:00",
        "favorability": "favorable",
        "activity": "Networking, learning, or wrapping up work"
      },
      {
        "time": "18:00 - 20:00",
        "favorability": "unfavorable",
        "activity": "Avoid Financial Decisions during this period"
      },
      {
        "time": "20:00 - 22:00",
        "favorability": "neutral",
        "activity": "Relaxation, reading, or preparing for tomorrow"
      }
    ],
    "personalized_recommendations": {
      "dos": [
        "Embrace new perspectives with an open heart.",
        "Practice active listening to foster understanding.",
        "Schedule brief moments for mindfulness throughout the day."
      ],
      "donts": [
        "Avoid snap judgments in complex situations.",
        "Don't let minor setbacks derail your overall progress.",
        "Refrain from overcommitting your time and energy."
      ]
    }
  },
  "Leo": {
    "Overall": "Leo, with Mars in your sign, you're brimming with energy and confidence today.  The Gemini influence encourages communication and adaptability. However, Saturn in Aries might present some challenges requiring patience and strategic thinking.  Use your natural charisma to navigate any obstacles.",
    "Auspicious Time": "11:00 AM - 1:00 PM",
    "Inauspicious Time": "6:00 PM - 8:00 PM",
    "Daily Wisdom & Suggestions": "Embrace the power of mindful communication and let go of impulsive reactions to maintain inner peace and achieve your goals.",
    "Detailed Predictions": {
      "Love & Relationships": {
        "Text": "Your passionate nature shines through, Leo, but avoid being too demanding. Open communication and understanding are key to strengthening your bonds. Single Leos might encounter unexpected romantic connections.",
        "percentage": "78"
      },
      "Career & Money": {
        "Text": "Your drive and ambition are rewarded today, particularly if you focus on collaborative projects.  Be mindful of potential financial risks, and avoid impulsive spending.  Trust your instincts in professional matters.",
        "percentage": "82"
      },
      "Health & Wellness": {
        "Text": "Your high energy levels may need careful management.  Prioritize rest and relaxation, and engage in activities that soothe your mind and body.  Mindful eating is crucial for maintaining balance.",
        "percentage": "90"
      },
      "Personal Growth": {
        "Text": "You are on the cusp of significant personal breakthroughs.  Embrace new perspectives and be open to learning from both successes and setbacks. Focus on self-reflection and personal development.",
        "percentage": "75"
      }
    },
    "lucky_elements": {
      "lucky_numbers": [
        7,
        11,
        22,
        34,
        45
      ],
      "lucky_colors": [
        "red",
        "deep blue",
        "forest green",
        "golden yellow"
      ]
    },
    "daily_timeline": [
      {
        "time": "6:00 - 8:00",
        "favorability": "neutral",
        "activity": "Morning reflection or light stretching"
      },
      {
        "time": "8:00 - 10:00",
        "favorability": "favorable",
        "activity": "Focus on important communications and planning"
      },
      {
        "time": "10:00 - 12:00",
        "favorability": "most-favorable",
        "activity": "Tackle creative projects or challenging tasks"
      },
      {
        "time": "12:00 - 14:00",
        "favorability": "neutral",
        "activity": "Lunch break, mindful eating, recharge"
      },
      {
        "time": "14:00 - 16:00",
        "favorability": "favorable",
        "activity": "Collaborative work or detail-oriented tasks"
      },
      {
        "time": "16:00 - 18:00",
        "favorability": "favorable",
        "activity": "Networking, learning, or wrapping up work"
      },
      {
        "time": "18:00 - 20:00",
        "favorability": "unfavorable",
        "activity": "Avoid Financial Decisions during this period"
      },
      {
        "time": "20:00 - 22:00",
        "favorability": "neutral",
        "activity": "Relaxation, reading, or preparing for tomorrow"
      }
    ],
    "personalized_recommendations": {
      "dos": [
        "Embrace new perspectives with an open heart.",
        "Practice active listening to foster understanding.",
        "Schedule brief moments for mindfulness throughout the day."
      ],
      "donts": [
        "Avoid snap judgments in complex situations.",
        "Don't let minor setbacks derail your overall progress.",
        "Refrain from overcommitting your time and energy."
      ]
    }
  },
  "Virgo": {
    "Overall": "Virgo, today's celestial alignment brings a blend of intense focus and creative energy.  The Moon in your sign amplifies your innate analytical abilities, while the Sun and Jupiter in Gemini encourage communication and expansion.  However, be mindful of potential energy drains and avoid impulsive decisions.",
    "Auspicious Time": "9:00 AM - 10:30 AM",
    "Inauspicious Time": "4:30 PM - 6:00 PM",
    "Daily Wisdom & Suggestions": "Listen to your intuition and trust your analytical skills, but temper your ambition with mindful self-care.  Prioritize clarity and effective communication, while remaining grounded in your practical nature.",
    "Detailed Predictions": {
      "Love & Relationships": {
        "Text": "Love life might feel a bit intense today. Open communication and honest expression are key to navigating any challenges.  Single Virgos may find themselves unexpectedly drawn to someone new.",
        "percentage": "75"
      },
      "Career & Money": {
        "Text": "Focus on detailed work and collaborative efforts.  Your meticulous nature will shine, leading to potential advancements or financial rewards. Avoid major financial decisions during the inauspicious time.",
        "percentage": "80"
      },
      "Health & Wellness": {
        "Text": "Pay close attention to your physical and mental wellbeing.  The Moon in Virgo heightens your sensitivity, so prioritize rest and mindful practices to avoid feeling overwhelmed.",
        "percentage": "85"
      },
      "Personal Growth": {
        "Text": "Embrace opportunities for learning and self-reflection.  Today's energy encourages introspection and personal growth.  Don't be afraid to step outside your comfort zone.",
        "percentage": "70"
      }
    },
    "lucky_elements": {
      "lucky_numbers": [
        7,
        11,
        22,
        34,
        45
      ],
      "lucky_colors": [
        "red",
        "deep blue",
        "forest green",
        "golden yellow"
      ]
    },
    "daily_timeline": [
      {
        "time": "6:00 - 8:00",
        "favorability": "neutral",
        "activity": "Morning reflection or light stretching"
      },
      {
        "time": "8:00 - 10:00",
        "favorability": "favorable",
        "activity": "Focus on important communications and planning"
      },
      {
        "time": "10:00 - 12:00",
        "favorability": "most-favorable",
        "activity": "Tackle creative projects or challenging tasks"
      },
      {
        "time": "12:00 - 14:00",
        "favorability": "neutral",
        "activity": "Lunch break, mindful eating, recharge"
      },
      {
        "time": "14:00 - 16:00",
        "favorability": "favorable",
        "activity": "Collaborative work or detail-oriented tasks"
      },
      {
        "time": "16:00 - 18:00",
        "favorability": "favorable",
        "activity": "Networking, learning, or wrapping up work"
      },
      {
        "time": "18:00 - 20:00",
        "favorability": "unfavorable",
        "activity": "Avoid Financial Decisions during this period"
      },
      {
        "time": "20:00 - 22:00",
        "favorability": "neutral",
        "activity": "Relaxation, reading, or preparing for tomorrow"
      }
    ],
    "personalized_recommendations": {
      "dos": [
        "Embrace new perspectives with an open heart.",
        "Practice active listening to foster understanding.",
        "Schedule brief moments for mindfulness throughout the day."
      ],
      "donts": [
        "Avoid snap judgments in complex situations.",
        "Don't let minor setbacks derail your overall progress.",
        "Refrain from overcommitting your time and energy."
      ]
    }
  },
  "Libra": {
    "Overall": "Libra, today's planetary alignment encourages a balanced approach to life.  The Sun and Jupiter in Gemini highlight communication and expansion, while the Moon in Virgo emphasizes attention to detail.  However, several planets in fire signs (Aries and Leo) might lead to impulsive decisions, so mindful planning is crucial for success.",
    "Auspicious Time": "9:00 AM - 10:30 AM",
    "Inauspicious Time": "4:30 PM - 6:00 PM",
    "Daily Wisdom & Suggestions": "Embrace thoughtful communication and prioritize your mental well-being.  Let go of perfectionism and focus on progress, not flawlessness.",
    "Detailed Predictions": {
      "Love & Relationships": {
        "Text": "Singles may encounter exciting new connections, but avoid rushing into anything serious.  Committed Libras should nurture open communication and address any underlying issues with honesty and compassion.",
        "percentage": "75"
      },
      "Career & Money": {
        "Text": "Focus on collaborative projects and meticulous work.  Avoid significant financial decisions today.  Opportunities for professional growth might present themselves through networking.",
        "percentage": "80"
      },
      "Health & Wellness": {
        "Text": "Prioritize mindfulness and stress reduction techniques.  Engage in gentle exercise and ensure you're getting enough rest.  Pay close attention to your diet and hydration.",
        "percentage": "90"
      },
      "Personal Growth": {
        "Text": "Embrace new learning experiences and expand your perspectives.  Challenge yourself to step outside your comfort zone, but do so with a well-defined plan.  Self-reflection will be beneficial.",
        "percentage": "70"
      }
    },
    "lucky_elements": {
      "lucky_numbers": [
        7,
        11,
        22,
        34,
        45
      ],
      "lucky_colors": [
        "red",
        "deep blue",
        "forest green",
        "golden yellow"
      ]
    },
    "daily_timeline": [
      {
        "time": "6:00 - 8:00",
        "favorability": "neutral",
        "activity": "Morning reflection or light stretching"
      },
      {
        "time": "8:00 - 10:00",
        "favorability": "favorable",
        "activity": "Focus on important communications and planning"
      },
      {
        "time": "10:00 - 12:00",
        "favorability": "most-favorable",
        "activity": "Tackle creative projects or challenging tasks"
      },
      {
        "time": "12:00 - 14:00",
        "favorability": "neutral",
        "activity": "Lunch break, mindful eating, recharge"
      },
      {
        "time": "14:00 - 16:00",
        "favorability": "favorable",
        "activity": "Collaborative work or detail-oriented tasks"
      },
      {
        "time": "16:00 - 18:00",
        "favorability": "favorable",
        "activity": "Networking, learning, or wrapping up work"
      },
      {
        "time": "18:00 - 20:00",
        "favorability": "unfavorable",
        "activity": "Avoid Financial Decisions during this period"
      },
      {
        "time": "20:00 - 22:00",
        "favorability": "neutral",
        "activity": "Relaxation, reading, or preparing for tomorrow"
      }
    ],
    "personalized_recommendations": {
      "dos": [
        "Embrace new perspectives with an open heart.",
        "Practice active listening to foster understanding.",
        "Schedule brief moments for mindfulness throughout the day."
      ],
      "donts": [
        "Avoid snap judgments in complex situations.",
        "Don't let minor setbacks derail your overall progress.",
        "Refrain from overcommitting your time and energy."
      ]
    }
  },
  "Scorpio": {
    "Overall": "Scorpio, today's planetary alignment encourages introspection and strategic planning.  The fiery influence of Mars and Venus might bring passionate energy, but the grounded presence of Virgo Moon urges you to channel this into productive endeavors.  Maintain a balanced approach, avoiding impulsive decisions, and focus on solidifying your goals.",
    "Auspicious Time": "9:00 AM - 10:30 AM",
    "Inauspicious Time": "4:30 PM - 6:00 PM",
    "Daily Wisdom & Suggestions": "Listen intently to both your inner voice and the needs of others;  wise action arises from thoughtful consideration and empathy.",
    "Detailed Predictions": {
      "Love & Relationships": {
        "Text": "Existing relationships may experience a surge of passion and intimacy.  Singles should remain open to new connections but exercise discernment.  Clear communication is key to navigating any potential conflicts.",
        "percentage": "85"
      },
      "Career & Money": {
        "Text": "Focus on detailed tasks and strategic planning.  Avoid risky financial ventures.  Your efforts will likely yield positive results, but patience and perseverance are essential for long-term success.",
        "percentage": "70"
      },
      "Health & Wellness": {
        "Text": "Prioritize mindful eating and relaxation techniques.  The day favors gentle exercise and stress-reducing activities. Pay attention to any signals your body is sending and address them promptly.",
        "percentage": "90"
      },
      "Personal Growth": {
        "Text": "Embrace new learning opportunities and step outside your comfort zone.  Today presents an ideal time for self-reflection and identifying areas for personal development.  Trust your intuition and embrace growth.",
        "percentage": "75"
      }
    },
    "lucky_elements": {
      "lucky_numbers": [
        7,
        11,
        22,
        34,
        45
      ],
      "lucky_colors": [
        "red",
        "deep blue",
        "forest green",
        "golden yellow"
      ]
    },
    "daily_timeline": [
      {
        "time": "6:00 - 8:00",
        "favorability": "neutral",
        "activity": "Morning reflection or light stretching"
      },
      {
        "time": "8:00 - 10:00",
        "favorability": "favorable",
        "activity": "Focus on important communications and planning"
      },
      {
        "time": "10:00 - 12:00",
        "favorability": "most-favorable",
        "activity": "Tackle creative projects or challenging tasks"
      },
      {
        "time": "12:00 - 14:00",
        "favorability": "neutral",
        "activity": "Lunch break, mindful eating, recharge"
      },
      {
        "time": "14:00 - 16:00",
        "favorability": "favorable",
        "activity": "Collaborative work or detail-oriented tasks"
      },
      {
        "time": "16:00 - 18:00",
        "favorability": "favorable",
        "activity": "Networking, learning, or wrapping up work"
      },
      {
        "time": "18:00 - 20:00",
        "favorability": "unfavorable",
        "activity": "Avoid Financial Decisions during this period"
      },
      {
        "time": "20:00 - 22:00",
        "favorability": "neutral",
        "activity": "Relaxation, reading, or preparing for tomorrow"
      }
    ],
    "personalized_recommendations": {
      "dos": [
        "Embrace new perspectives with an open heart.",
        "Practice active listening to foster understanding.",
        "Schedule brief moments for mindfulness throughout the day."
      ],
      "donts": [
        "Avoid snap judgments in complex situations.",
        "Don't let minor setbacks derail your overall progress.",
        "Refrain from overcommitting your time and energy."
      ]
    }
  },
  "Sagittarius": {
    "Overall": "Sagittarius, today's planetary alignment encourages you to embrace your adventurous spirit while maintaining a grounded approach.  The Sun and Jupiter in Gemini amplify your communication skills, while the Moon in Virgo urges attention to detail. Harness this energy for productive endeavors, but be mindful of potential impulsive decisions.",
    "Auspicious Time": "9:00 AM - 10:30 AM",
    "Inauspicious Time": "4:30 PM - 6:00 PM",
    "Daily Wisdom & Suggestions": "Listen to your intuition and trust your gut feelings, but carefully weigh the consequences of your actions before making any significant decisions.  Patience and thoughtful consideration will lead to greater success today.",
    "Detailed Predictions": {
      "Love & Relationships": {
        "Text": "Singles may encounter exciting new connections, while those in relationships should prioritize open communication to strengthen bonds. Be mindful of your partner's needs and express your own honestly.",
        "percentage": "85"
      },
      "Career & Money": {
        "Text": "Opportunities for professional advancement may arise, requiring decisive action.  Avoid risky financial ventures today; focus on steady progress and responsible financial management.",
        "percentage": "70"
      },
      "Health & Wellness": {
        "Text": "Prioritize mindful practices like meditation or yoga to manage stress.  Pay attention to your body's signals and ensure adequate rest.  A balanced diet will support your overall well-being.",
        "percentage": "90"
      },
      "Personal Growth": {
        "Text": "Embrace new learning experiences and expand your horizons.  Challenge yourself intellectually and creatively. Stepping outside your comfort zone will lead to significant personal growth.",
        "percentage": "75"
      }
    },
    "lucky_elements": {
      "lucky_numbers": [
        7,
        11,
        22,
        34,
        45
      ],
      "lucky_colors": [
        "red",
        "deep blue",
        "forest green",
        "golden yellow"
      ]
    },
    "daily_timeline": [
      {
        "time": "6:00 - 8:00",
        "favorability": "neutral",
        "activity": "Morning reflection or light stretching"
      },
      {
        "time": "8:00 - 10:00",
        "favorability": "favorable",
        "activity": "Focus on important communications and planning"
      },
      {
        "time": "10:00 - 12:00",
        "favorability": "most-favorable",
        "activity": "Tackle creative projects or challenging tasks"
      },
      {
        "time": "12:00 - 14:00",
        "favorability": "neutral",
        "activity": "Lunch break, mindful eating, recharge"
      },
      {
        "time": "14:00 - 16:00",
        "favorability": "favorable",
        "activity": "Collaborative work or detail-oriented tasks"
      },
      {
        "time": "16:00 - 18:00",
        "favorability": "favorable",
        "activity": "Networking, learning, or wrapping up work"
      },
      {
        "time": "18:00 - 20:00",
        "favorability": "unfavorable",
        "activity": "Avoid Financial Decisions during this period"
      },
      {
        "time": "20:00 - 22:00",
        "favorability": "neutral",
        "activity": "Relaxation, reading, or preparing for tomorrow"
      }
    ],
    "personalized_recommendations": {
      "dos": [
        "Embrace new perspectives with an open heart.",
        "Practice active listening to foster understanding.",
        "Schedule brief moments for mindfulness throughout the day."
      ],
      "donts": [
        "Avoid snap judgments in complex situations.",
        "Don't let minor setbacks derail your overall progress.",
        "Refrain from overcommitting your time and energy."
      ]
    }
  },
  "Capricorn": {
    "Overall": "Capricorn, today's planetary alignments suggest a day of balanced energy.  The influence of Mercury and Jupiter in Gemini encourages clear communication and strategic planning, while Saturn and Neptune in Aries might present unexpected challenges.  Maintain your focus and prioritize tasks effectively to navigate the day successfully.",
    "Auspicious Time": "9:00 AM - 11:00 AM",
    "Inauspicious Time": "3:00 PM - 5:00 PM",
    "Daily Wisdom & Suggestions": "Embrace patience and understanding in your interactions today, and remember that even small acts of mindfulness can significantly impact your well-being.",
    "Detailed Predictions": {
      "Love & Relationships": {
        "Text": "In matters of the heart, be open to new perspectives and avoid rushing into decisions.  Honest communication is key to strengthening existing bonds. Single Capricorns may find themselves drawn to someone unexpected.",
        "percentage": "70"
      },
      "Career & Money": {
        "Text": "Focus on details and collaborative efforts at work.  Avoid making significant financial decisions today.  Strategic planning and effective communication will enhance your professional prospects.",
        "percentage": "80"
      },
      "Health & Wellness": {
        "Text": "Prioritize mindful eating and relaxation today.  Engage in light exercise or stretching to relieve stress and boost your energy levels.  Listen to your body's needs.",
        "percentage": "85"
      },
      "Personal Growth": {
        "Text": "Embrace opportunities for learning and personal development.  Step outside your comfort zone and try something new.  Reflect on your progress and celebrate your achievements.",
        "percentage": "75"
      }
    },
    "lucky_elements": {
      "lucky_numbers": [
        7,
        11,
        22,
        34,
        45
      ],
      "lucky_colors": [
        "red",
        "deep blue",
        "forest green",
        "golden yellow"
      ]
    },
    "daily_timeline": [
      {
        "time": "6:00 - 8:00",
        "favorability": "neutral",
        "activity": "Morning reflection or light stretching"
      },
      {
        "time": "8:00 - 10:00",
        "favorability": "favorable",
        "activity": "Focus on important communications and planning"
      },
      {
        "time": "10:00 - 12:00",
        "favorability": "most-favorable",
        "activity": "Tackle creative projects or challenging tasks"
      },
      {
        "time": "12:00 - 14:00",
        "favorability": "neutral",
        "activity": "Lunch break, mindful eating, recharge"
      },
      {
        "time": "14:00 - 16:00",
        "favorability": "favorable",
        "activity": "Collaborative work or detail-oriented tasks"
      },
      {
        "time": "16:00 - 18:00",
        "favorability": "favorable",
        "activity": "Networking, learning, or wrapping up work"
      },
      {
        "time": "18:00 - 20:00",
        "favorability": "unfavorable",
        "activity": "Avoid Financial Decisions during this period"
      },
      {
        "time": "20:00 - 22:00",
        "favorability": "neutral",
        "activity": "Relaxation, reading, or preparing for tomorrow"
      }
    ],
    "personalized_recommendations": {
      "dos": [
        "Embrace new perspectives with an open heart.",
        "Practice active listening to foster understanding.",
        "Schedule brief moments for mindfulness throughout the day."
      ],
      "donts": [
        "Avoid snap judgments in complex situations.",
        "Don't let minor setbacks derail your overall progress.",
        "Refrain from overcommitting your time and energy."
      ]
    }
  },
  "Aquarius": {
    "Overall": "Aquarius, today's planetary alignment brings a blend of creative energy and intellectual stimulation.  With the Sun, Mercury, and Jupiter in Gemini, communication and mental agility are highlighted. However, Pluto's presence in your sign suggests a period of deep transformation, requiring introspection and careful consideration of your actions.  Embrace the opportunities for growth, but proceed with mindful intention.",
    "Auspicious Time": "9:00 AM - 10:30 AM",
    "Inauspicious Time": "4:30 PM - 6:00 PM",
    "Daily Wisdom & Suggestions": "Listen intently to understand others' perspectives before reacting, and prioritize self-reflection to navigate internal transformations effectively.",
    "Detailed Predictions": {
      "Love & Relationships": {
        "Text": "Singles may encounter unexpected romantic connections.  Those in committed relationships should prioritize open communication and address any underlying issues with empathy and understanding.  Focus on strengthening the bond through shared activities and meaningful conversations.",
        "percentage": "78"
      },
      "Career & Money": {
        "Text": "Innovative ideas will be welcomed in the workplace.  Financial matters require careful planning and avoidance of impulsive decisions.  This is a good time to strategize for future growth and explore new opportunities, but avoid significant financial commitments during the inauspicious time.",
        "percentage": "70"
      },
      "Health & Wellness": {
        "Text": "Prioritize mindfulness and stress-reducing activities.  Pay attention to your body's signals and ensure you're getting enough rest.  Engage in gentle exercise and maintain a balanced diet to boost your overall well-being.",
        "percentage": "85"
      },
      "Personal Growth": {
        "Text": "Embrace personal transformation with courage and self-compassion.  This is a time for deep introspection and self-discovery.  Identify limiting beliefs and actively work towards personal growth and liberation.",
        "percentage": "75"
      }
    },
    "lucky_elements": {
      "lucky_numbers": [
        7,
        11,
        22,
        34,
        45
      ],
      "lucky_colors": [
        "red",
        "deep blue",
        "forest green",
        "golden yellow"
      ]
    },
    "daily_timeline": [
      {
        "time": "6:00 - 8:00",
        "favorability": "neutral",
        "activity": "Morning reflection or light stretching"
      },
      {
        "time": "8:00 - 10:00",
        "favorability": "favorable",
        "activity": "Focus on important communications and planning"
      },
      {
        "time": "10:00 - 12:00",
        "favorability": "most-favorable",
        "activity": "Tackle creative projects or challenging tasks"
      },
      {
        "time": "12:00 - 14:00",
        "favorability": "neutral",
        "activity": "Lunch break, mindful eating, recharge"
      },
      {
        "time": "14:00 - 16:00",
        "favorability": "favorable",
        "activity": "Collaborative work or detail-oriented tasks"
      },
      {
        "time": "16:00 - 18:00",
        "favorability": "favorable",
        "activity": "Networking, learning, or wrapping up work"
      },
      {
        "time": "18:00 - 20:00",
        "favorability": "unfavorable",
        "activity": "Avoid Financial Decisions during this period"
      },
      {
        "time": "20:00 - 22:00",
        "favorability": "neutral",
        "activity": "Relaxation, reading, or preparing for tomorrow"
      }
    ],
    "personalized_recommendations": {
      "dos": [
        "Embrace new perspectives with an open heart.",
        "Practice active listening to foster understanding.",
        "Schedule brief moments for mindfulness throughout the day."
      ],
      "donts": [
        "Avoid snap judgments in complex situations.",
        "Don't let minor setbacks derail your overall progress.",
        "Refrain from overcommitting your time and energy."
      ]
    }
  },
  "Pisces": {
    "Overall": "Pisces, today's celestial alignment encourages introspection and mindful action.  The blend of Gemini's intellectual energy and Virgo's practicality will help you navigate complex situations with grace.  Trust your intuition, but also pay attention to the details.  A period of creative exploration awaits you.",
    "Auspicious Time": "9:00 AM - 10:30 AM",
    "Inauspicious Time": "4:30 PM - 6:00 PM",
    "Daily Wisdom & Suggestions": "Embrace new perspectives while avoiding snap judgments; listen actively to foster understanding, but don't let minor setbacks derail your progress.",
    "Detailed Predictions": {
      "Love & Relationships": {
        "Text": "Love life thrives on open communication today.  Express your feelings honestly and listen attentively to your partner.  Singles might encounter unexpected connections through shared interests or activities.",
        "percentage": "85"
      },
      "Career & Money": {
        "Text": "Focus on meticulous work and detail-oriented tasks for professional success.  Avoid making significant financial decisions today.  Creative projects may yield unexpected rewards.",
        "percentage": "70"
      },
      "Health & Wellness": {
        "Text": "Prioritize mindful eating and relaxation techniques to maintain a balanced well-being.  Engage in gentle exercise or stretching to release tension.  Listen to your body's needs.",
        "percentage": "90"
      },
      "Personal Growth": {
        "Text": "Today is ideal for personal reflection and setting intentions.  Explore new learning opportunities or creative pursuits.  Embrace self-compassion and celebrate small victories.",
        "percentage": "75"
      }
    },
    "lucky_elements": {
      "lucky_numbers": [
        7,
        11,
        22,
        34,
        45
      ],
      "lucky_colors": [
        "red",
        "deep blue",
        "forest green",
        "golden yellow"
      ]
    },
    "daily_timeline": [
      {
        "time": "6:00 - 8:00",
        "favorability": "neutral",
        "activity": "Morning reflection or light stretching"
      },
      {
        "time": "8:00 - 10:00",
        "favorability": "favorable",
        "activity": "Focus on important communications and planning"
      },
      {
        "time": "10:00 - 12:00",
        "favorability": "most-favorable",
        "activity": "Tackle creative projects or challenging tasks"
      },
      {
        "time": "12:00 - 14:00",
        "favorability": "neutral",
        "activity": "Lunch break, mindful eating, recharge"
      },
      {
        "time": "14:00 - 16:00",
        "favorability": "favorable",
        "activity": "Collaborative work or detail-oriented tasks"
      },
      {
        "time": "16:00 - 18:00",
        "favorability": "favorable",
        "activity": "Networking, learning, or wrapping up work"
      },
      {
        "time": "18:00 - 20:00",
        "favorability": "unfavorable",
        "activity": "Avoid Financial Decisions during this period"
      },
      {
        "time": "20:00 - 22:00",
        "favorability": "neutral",
        "activity": "Relaxation, reading, or preparing for tomorrow"
      }
    ],
    "personalized_recommendations": {
      "dos": [
        "Embrace new perspectives with an open heart.",
        "Practice active listening to foster understanding.",
        "Schedule brief moments for mindfulness throughout the day."
      ],
      "donts": [
        "Avoid snap judgments in complex situations.",
        "Don't let minor setbacks derail your overall progress.",
        "Refrain from overcommitting your time and energy."
      ]
    }
  }
}